Metadata-Version: 1.0
Name: django-datasync
Version: 0.0.1.dev0
Summary: Sync environment
Home-page: https://bitbucket.org/geert2705/django-datasync
Author: Geert Dekkers
Author-email: geert@djangowebstudio.com
License: MIT
Platform: UNKNOWN
